healsparse/__init__.py
healsparse/cat_healsparse_files.py
healsparse/fits_shim.py
healsparse/geom.py
healsparse/healSparseCoverage.py
healsparse/healSparseMap.py
healsparse/healSparseRandoms.py
healsparse/io_coverage.py
healsparse/io_coverage_fits.py
healsparse/io_coverage_parquet.py
healsparse/io_map.py
healsparse/io_map_fits.py
healsparse/io_map_hdf5.py
healsparse/io_map_healpix.py
healsparse/io_map_parquet.py
healsparse/operations.py
healsparse/packedBoolArray.py
healsparse/parquet_shim.py
healsparse/utils.py
healsparse-1.12.1.dist-info/licenses/LICENSE
healsparse-1.12.1.dist-info/METADATA
healsparse-1.12.1.dist-info/WHEEL
healsparse-1.12.1.dist-info/top_level.txt
healsparse-1.12.1.dist-info/zip-safe
healsparse-1.12.1.dist-info/RECORD
