Metadata-Version: 2.4
Name: healsparse
Version: 1.12.1
Summary: Sparse healpix maps and geometry library
Home-page: https://github.com/lsstdesc/healsparse
Author: Eli Rykoff, Javier Sanchez, and the Dark Energy Science Collaboration
Author-email: erykoff@stanford.edu
Classifier: Intended Audience :: Science/Research
Classifier: License :: OSI Approved :: GNU General Public License v3 or later (GPLv3+)
Classifier: Operating System :: POSIX :: Linux
Classifier: Operating System :: MacOS
Classifier: Operating System :: Microsoft :: Windows
Classifier: Programming Language :: C
Classifier: Programming Language :: Python :: 3
Classifier: Programming Language :: Python :: 3.7
Classifier: Programming Language :: Python :: 3.8
Classifier: Programming Language :: Python :: 3.9
Classifier: Programming Language :: Python :: 3.10
Classifier: Programming Language :: Python :: 3.11
Requires-Python: >=3.7
License-File: LICENSE
Requires-Dist: numpy
Requires-Dist: hpgeom>=1.2.0
Requires-Dist: astropy
Provides-Extra: test
Requires-Dist: pytest; extra == "test"
Requires-Dist: flake8; extra == "test"
Provides-Extra: parquet
Requires-Dist: pyarrow>=5.0.0; extra == "parquet"
Provides-Extra: test-with-healpy
Requires-Dist: healpy; extra == "test-with-healpy"
Provides-Extra: fitsio
Requires-Dist: fitsio; extra == "fitsio"
Provides-Extra: hdf5
Requires-Dist: h5py; extra == "hdf5"
Dynamic: license-file
